airflow_code_editor/__init__.py
airflow_code_editor/airflow_code_editor.py
airflow_code_editor/app_builder_view.py
airflow_code_editor/auth.py
airflow_code_editor/code_editor_view.py
airflow_code_editor/commons.py
airflow_code_editor/flask_admin_view.py
airflow_code_editor/utils.py
airflow_code_editor/static/bootstrap-dialog.js
airflow_code_editor/static/codemirror.js
airflow_code_editor/static/emacs.js
airflow_code_editor/static/gitweb.js
airflow_code_editor/static/sublime.js
airflow_code_editor/static/vim.js
airflow_code_editor/static/addon/comment/comment.js
airflow_code_editor/static/addon/comment/continuecomment.js
airflow_code_editor/static/addon/dialog/dialog.css
airflow_code_editor/static/addon/dialog/dialog.js
airflow_code_editor/static/addon/display/autorefresh.js
airflow_code_editor/static/addon/display/fullscreen.css
airflow_code_editor/static/addon/display/fullscreen.js
airflow_code_editor/static/addon/display/panel.js
airflow_code_editor/static/addon/display/placeholder.js
airflow_code_editor/static/addon/display/rulers.js
airflow_code_editor/static/addon/edit/closebrackets.js
airflow_code_editor/static/addon/edit/closetag.js
airflow_code_editor/static/addon/edit/continuelist.js
airflow_code_editor/static/addon/edit/matchbrackets.js
airflow_code_editor/static/addon/edit/matchtags.js
airflow_code_editor/static/addon/edit/trailingspace.js
airflow_code_editor/static/addon/fold/brace-fold.js
airflow_code_editor/static/addon/fold/comment-fold.js
airflow_code_editor/static/addon/fold/foldcode.js
airflow_code_editor/static/addon/fold/foldgutter.css
airflow_code_editor/static/addon/fold/foldgutter.js
airflow_code_editor/static/addon/fold/indent-fold.js
airflow_code_editor/static/addon/fold/markdown-fold.js
airflow_code_editor/static/addon/fold/xml-fold.js
airflow_code_editor/static/addon/hint/anyword-hint.js
airflow_code_editor/static/addon/hint/css-hint.js
airflow_code_editor/static/addon/hint/html-hint.js
haiqv_streaming_dag_editor-1.0.0.dist-info/LICENSE
haiqv_streaming_dag_editor-1.0.0.dist-info/METADATA
haiqv_streaming_dag_editor-1.0.0.dist-info/WHEEL
haiqv_streaming_dag_editor-1.0.0.dist-info/entry_points.txt
haiqv_streaming_dag_editor-1.0.0.dist-info/top_level.txt
haiqv_streaming_dag_editor-1.0.0.dist-info/RECORD
