Metadata-Version: 2.1
Name: haiqv-streaming-dag-editor
Version: 1.0.0
Summary: A code editor and file manager about dag for haiqv-streaming
Home-page: UNKNOWN
Author: EngUt _ (origin : Andrea Bonomi)
Author-email: itb001@hanwhasystem.com
License: Apache License, Version 2.0
Platform: UNKNOWN
Classifier: Operating System :: OS Independent
Classifier: Programming Language :: Python
Classifier: Topic :: Software Development :: Libraries :: Python Modules
Classifier: Programming Language :: Python :: 3
Classifier: Programming Language :: Python :: 3.4
Classifier: Programming Language :: Python :: 3.5
Classifier: Programming Language :: Python :: 3.6
Classifier: Programming Language :: Python :: 3.7
Classifier: Programming Language :: Python :: 3.8
Requires-Dist: apache-airflow
